[{"Applicant ID":1,"School Name":"Brown University","GPA":"3.0","Degree":"Phd","Location":"New York City","Gender":"F","Veteran status":"1","Work authorization":"0","Disability":"1","Ethnicity":"1","Role 1":"ML Engineer","Start 1":"4\/17","End 1":"11\/21","Role 2":"Chef","Start 2":"5\/13","End 2":"3\/14","Role 3":"Junior SWE","Start 3":"12\/11","End 3":"9\/13"},{"Applicant ID":2,"School Name":"Columbia University","GPA":"4.0","Degree":"Bachelors","Location":"Los Angeles","Gender":"N\/A","Veteran status":"N\/A","Work authorization":"1","Disability":"0","Ethnicity":"3","Role 1":"N\/A","Start 1":"N\/A","End 1":"N\/A","Role 2":"N\/A","Start 2":"N\/A","End 2":"N\/A","Role 3":"N\/A","Start 3":"N\/A","End 3":"N\/A"},{"Applicant ID":3,"School Name":"Brown University","GPA":"2.7","Degree":"Phd","Location":"Washington D.C.","Gender":"N\/A","Veteran status":"0","Work authorization":"0","Disability":"N\/A","Ethnicity":"2","Role 1":"Data scientist","Start 1":"6\/10","End 1":"5\/20","Role 2":"Lawyer","Start 2":"5\/11","End 2":"9\/22","Role 3":"Bus Driver","Start 3":"1\/21","End 3":"11\/22"},{"Applicant ID":4,"School Name":"Columbia University","GPA":"3.8","Degree":"Bachelors","Location":"Detroit","Gender":"F","Veteran status":"1","Work authorization":"0","Disability":"1","Ethnicity":"4","Role 1":"Lawyer","Start 1":"4\/11","End 1":"3\/19","Role 2":"Data scientist","Start 2":"6\/19","End 2":"10\/23","Role 3":"N\/A","Start 3":"N\/A","End 3":"N\/A"}]